odoo/addons/website_cookiebot/README.rst
odoo/addons/website_cookiebot/__init__.py
odoo/addons/website_cookiebot/__manifest__.py
odoo/addons/website_cookiebot/i18n/de.po
odoo/addons/website_cookiebot/i18n/es.po
odoo/addons/website_cookiebot/i18n/it.po
odoo/addons/website_cookiebot/i18n/website_cookiebot.pot
odoo/addons/website_cookiebot/models/__init__.py
odoo/addons/website_cookiebot/models/website.py
odoo/addons/website_cookiebot/readme/CONFIGURE.md
odoo/addons/website_cookiebot/readme/CONTRIBUTORS.md
odoo/addons/website_cookiebot/readme/DESCRIPTION.md
odoo/addons/website_cookiebot/readme/USAGE.md
odoo/addons/website_cookiebot/static/description/icon.png
odoo/addons/website_cookiebot/static/description/index.html
odoo/addons/website_cookiebot/static/description/screenshot.png
odoo/addons/website_cookiebot/templates/assets.xml
odoo/addons/website_cookiebot/templates/website.xml
odoo/addons/website_cookiebot/tests/__init__.py
odoo/addons/website_cookiebot/tests/test_website_cookiebot.py
odoo/addons/website_cookiebot/wizards/__init__.py
odoo/addons/website_cookiebot/wizards/res_config_settings.py
odoo/addons/website_cookiebot/wizards/res_config_settings_views.xml
odoo_addon_website_cookiebot-18.0.1.0.0.2.dist-info/METADATA
odoo_addon_website_cookiebot-18.0.1.0.0.2.dist-info/WHEEL
odoo_addon_website_cookiebot-18.0.1.0.0.2.dist-info/top_level.txt
odoo_addon_website_cookiebot-18.0.1.0.0.2.dist-info/RECORD
